desktop_bridge/sensor_bridge.py
vertac_bridge-0.2.1.dist-info/METADATA
vertac_bridge-0.2.1.dist-info/WHEEL
vertac_bridge-0.2.1.dist-info/entry_points.txt
vertac_bridge-0.2.1.dist-info/top_level.txt
vertac_bridge-0.2.1.dist-info/RECORD
