Metadata-Version: 2.4
Name: vertac-bridge
Version: 0.2.1
Summary: VerTac Sensor Data Bridge - Lightweight connector for sensor data ingestion
Home-page: https://github.com/your-org/vertac-bridge
Author: VerTac Team
Author-email: VerTac Team <info@vertac.dev>
License: MIT
Project-URL: Homepage, https://github.com/your-org/vertac-bridge
Project-URL: Documentation, https://vertac-bridge.readthedocs.io
Project-URL: Repository, https://github.com/your-org/vertac-bridge.git
Project-URL: Issues, https://github.com/your-org/vertac-bridge/issues
Keywords: sensor,bridge,data-ingestion,monitoring,api-client
Classifier: Development Status :: 4 - Beta
Classifier: Environment :: Console
Classifier: Intended Audience :: Developers
Classifier: Intended Audience :: Manufacturing
Classifier: License :: OSI Approved :: MIT License
Classifier: Operating System :: OS Independent
Classifier: Programming Language :: Python :: 3
Classifier: Programming Language :: Python :: 3.9
Classifier: Programming Language :: Python :: 3.10
Classifier: Programming Language :: Python :: 3.11
Classifier: Programming Language :: Python :: 3.12
Classifier: Topic :: System :: Monitoring
Requires-Python: >=3.9
Requires-Dist: requests>=2.31.0
Requires-Dist: python-dotenv>=1.0.0
Provides-Extra: dev
Requires-Dist: pytest>=7.0.0; extra == "dev"
Requires-Dist: black>=23.0.0; extra == "dev"
Requires-Dist: isort>=5.12.0; extra == "dev"
Requires-Dist: flake8>=6.0.0; extra == "dev"
Requires-Dist: mypy>=1.0.0; extra == "dev"
Dynamic: author
Dynamic: home-page
Dynamic: requires-python
